types_xlrd-2.0.0.20251020.dist-info/licenses/LICENSE
xlrd-stubs/METADATA.toml
xlrd-stubs/__init__.pyi
xlrd-stubs/biffh.pyi
xlrd-stubs/book.pyi
xlrd-stubs/compdoc.pyi
xlrd-stubs/formatting.pyi
xlrd-stubs/formula.pyi
xlrd-stubs/info.pyi
xlrd-stubs/py.typed
xlrd-stubs/sheet.pyi
xlrd-stubs/timemachine.pyi
xlrd-stubs/xldate.pyi
types_xlrd-2.0.0.20251020.dist-info/METADATA
types_xlrd-2.0.0.20251020.dist-info/WHEEL
types_xlrd-2.0.0.20251020.dist-info/top_level.txt
types_xlrd-2.0.0.20251020.dist-info/RECORD
